active_learning_img_augmentation_utils/__init__.py
active_learning_img_augmentation_utils/models/SCNN.py
active_learning_img_augmentation_utils/models/__init__.py
active_learning_img_augmentation_utils/utils/__init__.py
active_learning_img_augmentation_utils/utils/ds.py
active_learning_img_augmentation_utils/utils/util.py
active_learning_img_augmentation_utils-1.0.1.dist-info/LICENSE
active_learning_img_augmentation_utils-1.0.1.dist-info/METADATA
active_learning_img_augmentation_utils-1.0.1.dist-info/WHEEL
active_learning_img_augmentation_utils-1.0.1.dist-info/top_level.txt
active_learning_img_augmentation_utils-1.0.1.dist-info/RECORD
